CTRegisterMicroserviceFlask/__init__.py
CTRegisterMicroserviceFlask/errors.py
CTRegisterMicroserviceFlask-0.5.0.dist-info/LICENSE
CTRegisterMicroserviceFlask-0.5.0.dist-info/METADATA
CTRegisterMicroserviceFlask-0.5.0.dist-info/WHEEL
CTRegisterMicroserviceFlask-0.5.0.dist-info/top_level.txt
CTRegisterMicroserviceFlask-0.5.0.dist-info/RECORD
