Metadata-Version: 2.1
Name: CTRegisterMicroserviceFlask
Version: 0.5.0
Summary: Library to interact with the Control-Tower api-gateway (register, do requests to other microservices, etc)
Home-page: UNKNOWN
Author: Vizzuality
Author-email: info@vizzuality.com
License: MIT
Platform: UNKNOWN
Requires-Dist: flask
Requires-Dist: requests
Provides-Extra: dev
Requires-Dist: pytest (==5.2.2) ; extra == 'dev'
Requires-Dist: pytest-cov (==2.8.1) ; extra == 'dev'
Requires-Dist: pytest-mock (==1.11.1) ; extra == 'dev'
Requires-Dist: codecov (==2.0.15) ; extra == 'dev'
Requires-Dist: requests-mock (==1.7.0) ; extra == 'dev'
